deepxromm/__init__.py
deepxromm/analyzer.py
deepxromm/autocorrector.py
deepxromm/deepxromm.py
deepxromm/default_config.yaml
deepxromm/network.py
deepxromm/project.py
deepxromm/xma_data_processor.py
deepxromm/xrommtools.py
deepxromm-0.2.11.dist-info/licenses/LICENSE
deepxromm-0.2.11.dist-info/METADATA
deepxromm-0.2.11.dist-info/WHEEL
deepxromm-0.2.11.dist-info/top_level.txt
deepxromm-0.2.11.dist-info/RECORD
