Metadata-Version: 2.4
Name: deepxromm
Version: 0.2.11
Summary: A set of user-friendly tools for DeepLabCut-XMALab marker tracking
Author-email: Sam DeLap <sjcdelap@gmail.com>
License: MIT License
Project-URL: Homepage, https://github.com/sam-delap/deepxromm
Project-URL: Documentation, https://sam-delap.github.io/deepxromm
Keywords: deepxromm,XMALab,DeepLabCut,XROMM
Classifier: Programming Language :: Python :: 3
Classifier: License :: OSI Approved :: MIT License
Classifier: Operating System :: OS Independent
Requires-Python: >=3.10
License-File: LICENSE
Requires-Dist: blend_modes
Requires-Dist: deeplabcut[tf]
Requires-Dist: imagehash
Requires-Dist: numpy<2
Provides-Extra: cli
Requires-Dist: ipython; extra == "cli"
Dynamic: license-file
